arete/__init__.py
arete/__main__.py
arete/agent.py
arete/consts.py
arete/main.py
arete/mcp_server.py
arete/py.typed
arete/server.py
arete/application/__init__.py
arete/application/config.py
arete/application/converter.py
arete/application/factory.py
arete/application/graph_resolver.py
arete/application/id_service.py
arete/application/parser.py
arete/application/pipeline.py
arete/application/queue_builder.py
arete/application/stats_service.py
arete/application/vault_service.py
arete/application/wizard.py
arete/application/stats/metrics_calculator.py
arete/application/stats/service.py
arete/application/utils/__init__.py
arete/application/utils/common.py
arete/application/utils/consts.py
arete/application/utils/fs.py
arete/application/utils/logging.py
arete/application/utils/media.py
arete/application/utils/text.py
arete/application/utils/yaml.py
arete/domain/__init__.py
arete/domain/graph.py
arete/domain/interfaces.py
arete/domain/models.py
arete/domain/stats/models.py
arete/domain/stats/ports.py
arete/infrastructure/__init__.py
arete/infrastructure/adapters/anki_connect.py
arete/infrastructure/adapters/anki_direct.py
arete/infrastructure/adapters/fs.py
arete/infrastructure/adapters/stats/__init__.py
arete/infrastructure/adapters/stats/connect_stats.py
arete/infrastructure/adapters/stats/direct_stats.py
arete/infrastructure/anki/__init__.py
arete/infrastructure/anki/repository.py
arete/infrastructure/persistence/cache.py
arete/interface/__init__.py
arete/interface/cli.py
arete-2.0.1.dist-info/METADATA
arete-2.0.1.dist-info/WHEEL
arete-2.0.1.dist-info/entry_points.txt
arete-2.0.1.dist-info/licenses/LICENSE
arete-2.0.1.dist-info/RECORD
