Metadata-Version: 2.4
Name: arete
Version: 2.0.1
Summary: A robust, fast, and feature-rich CLI for syncing Obsidian vault to Anki.
Project-URL: Repository, https://github.com/Adanato/Arete
Author-email: Adam Nguyen <AdanatoNw@gmail.com>
License-Expression: GPL-3.0
License-File: LICENSE
Keywords: anki,obsidian,spaced-repetition,sync
Classifier: Development Status :: 4 - Beta
Classifier: Environment :: Console
Classifier: Intended Audience :: End Users/Desktop
Classifier: License :: OSI Approved :: GNU General Public License v3 (GPLv3)
Classifier: Programming Language :: Python :: 3.11
Classifier: Topic :: Education
Requires-Python: >=3.12
Requires-Dist: anki==24.4.1
Requires-Dist: fastapi>=0.109.0
Requires-Dist: httpx>=0.28.1
Requires-Dist: markdown>=3.10
Requires-Dist: pydantic-settings[toml]>=2.12.0
Requires-Dist: pydantic>=2.12.5
Requires-Dist: python-ulid>=3.0.0
Requires-Dist: pyyaml>=6.0.3
Requires-Dist: requests>=2.31.0
Requires-Dist: tqdm>=4.67.1
Requires-Dist: typer[all]>=0.21.0
Requires-Dist: uvicorn[standard]>=0.27.0
Requires-Dist: watchdog>=4.0.0
Provides-Extra: agent
Requires-Dist: atomic-agents>=2.6.0; extra == 'agent'
Requires-Dist: google-generativeai>=0.8.0; extra == 'agent'
Requires-Dist: instructor>=1.0.0; extra == 'agent'
Requires-Dist: mcp>=1.0.0; extra == 'agent'
Requires-Dist: openai>=1.0.0; extra == 'agent'
